Metadata-Version: 2.1
Name: pydyndns
Version: 1.2.1
Summary: Sends dynamic DNS updates to a DNS server.
Home-page: https://gitlab.com/Hawk777/pydyndns
Author: Christopher Head
Classifier: Development Status :: 5 - Production/Stable
Classifier: Environment :: No Input/Output (Daemon)
Classifier: Intended Audience :: System Administrators
Classifier: License :: OSI Approved :: MIT License
Classifier: Operating System :: OS Independent
Classifier: Programming Language :: Python :: 3 :: Only
Classifier: Topic :: Internet :: Name Service (DNS)
License-File: LICENSE.txt
